dictionary/__init__.py
dictionary/dictionary.py
simple_homework_CS453_123_dictionary-2.0.3.dist-info/METADATA
simple_homework_CS453_123_dictionary-2.0.3.dist-info/WHEEL
simple_homework_CS453_123_dictionary-2.0.3.dist-info/top_level.txt
simple_homework_CS453_123_dictionary-2.0.3.dist-info/RECORD
