Metadata-Version: 2.1
Name: simple-homework-CS453-123-dictionary
Version: 2.0.3
Summary: UNKNOWN
Author: Emre Derman
License: UNKNOWN
Platform: UNKNOWN
Requires-Python: >=3.8
Requires-Dist: requests (>=2.23.0)
